{
    "type": "FeatureCollection",
    "crs": {
        "type": "name",
        "properties": {
            "name": "urn:ogc:def:crs:OGC:1.3:CRS84"
        }
    },
    "features": [
        {
            "type": "Feature",
            "properties": {
                "Name": "Label with marker",
                "Description": ""
            },
            "geometry": {
                "type": "Point",
                "coordinates": [
                    7.3702,
                    47.276859973195158
                ]
            }
        }
    ]
}
